setup.cfg
setup.py
black_hole.egg-info/PKG-INFO
black_hole.egg-info/SOURCES.txt
black_hole.egg-info/dependency_links.txt
black_hole.egg-info/entry_points.txt
black_hole.egg-info/top_level.txt
black_hole.egg-info/zip-safe
blackhole/__init__.py
blackhole/blackhole.py
blackhole/cronwalk.py
blackhole/relativedelta.py
blackhole/shortcut.py
blackhole/timeparser.py