Metadata-Version: 1.0
Name: black-hole
Version: 0.0.3
Summary: 一个增强时间管理库
Home-page: https://github.com/liuhao1024/black-hole
Author: liuhao1024
Author-email: edve@163.com
License: MIT License
Keywords: datetime,calendar,time
Platform: UNKNOWN
